<?xml version="1.0" ?>
<map>
    <tileset tileset_file="resources/tileset_01.xml" />
    <nodes>
        <node surface_id="2" x="47" y="-25" z="0" layer="3" angle="0.000000" scale="1.000000" trans="255" mirror_x="0" mirror_y="0" tint_r="255" tint_g="255" tint_b="255" if_wrap="0" region_width="0" region_height="0" />
        <node surface_id="2" x="136" y="-25" z="0" layer="3" angle="0.000000" scale="1.000000" trans="255" mirror_x="0" mirror_y="0" tint_r="255" tint_g="255" tint_b="255" if_wrap="0" region_width="0" region_height="0" />
        <node surface_id="2" x="213" y="-21" z="0" layer="3" angle="0.000000" scale="1.000000" trans="255" mirror_x="0" mirror_y="0" tint_r="255" tint_g="255" tint_b="255" if_wrap="0" region_width="0" region_height="0" />
        <node surface_id="2" x="296" y="-24" z="0" layer="3" angle="0.000000" scale="1.000000" trans="255" mirror_x="0" mirror_y="0" tint_r="255" tint_g="255" tint_b="255" if_wrap="0" region_width="0" region_height="0" />
        <node surface_id="2" x="391" y="-23" z="0" layer="3" angle="0.000000" scale="1.000000" trans="255" mirror_x="0" mirror_y="0" tint_r="255" tint_g="255" tint_b="255" if_wrap="0" region_width="0" region_height="0" />
        <node surface_id="2" x="473" y="-21" z="0" layer="3" angle="0.000000" scale="1.000000" trans="255" mirror_x="0" mirror_y="0" tint_r="255" tint_g="255" tint_b="255" if_wrap="0" region_width="0" region_height="0" />
        <node surface_id="9" x="258" y="-250" z="0" layer="3" angle="0.000000" scale="1.000000" trans="255" mirror_x="0" mirror_y="0" tint_r="255" tint_g="255" tint_b="255" if_wrap="0" region_width="0" region_height="0" />
    </nodes>
</map>
